Metadata-Version: 1.1
Name: pd-validator
Version: 1.0.0
Summary: pandas DataFrame validation library
Home-page: https://github.com/nrbontha/pd-validator
Author: nrbontha
Author-email: nrbontha@gmail.com
License: UNKNOWN
Keywords: pandas,data,validation,analysis
Platform: UNKNOWN
Classifier: Development Status :: 4 - Beta
Classifier: Intended Audience :: Developers
Classifier: Programming Language :: Python :: 3
Classifier: Programming Language :: Python :: 2
Classifier: License :: OSI Approved :: MIT License
Classifier: Operating System :: OS Independent
